{
 "custom_fields": [],
 "custom_perms": [],
 "doctype": "Lead",
 "property_setters": [
  {
   "_assign": null,
   "_comments": null,
   "_liked_by": null,
   "_user_tags": null,
   "creation": "2021-11-09 15:58:36.239447",
   "default_value": null,
   "doc_type": "Lead",
   "docstatus": 0,
   "doctype_or_field": "DocField",
   "field_name": "status",
   "idx": 0,
   "modified": "2021-11-09 15:58:36.239447",
   "modified_by": "Administrator",
   "name": "Lead-status-options",
   "owner": "Administrator",
   "parent": null,
   "parentfield": null,
   "parenttype": null,
   "property": "options",
   "property_type": "Text",
   "row_name": null,
   "value": "Lead\nOpen\nReplied\nOpportunity\nQuotation\nLost Quotation\nInterested\nConverted\nDo Not Contact\nClose"
  }
 ],
 "sync_on_migrate": 1
}
